{
  "meta": {
    "version": "1.0",
    "exported": "2026-05-22T00:00:00Z",
    "council": "LGAM Reference"
  },
  "taxonomy": {
    "layers": [
      { "id": "capabilities", "label": "Capabilities", "colour": "#000080" },
      { "id": "business", "label": "Business Areas", "colour": "#0000FF" },
      { "id": "corporate", "label": "Corporate Areas", "colour": "#696969" },
      { "id": "foundational-technology", "label": "Foundational Technology", "colour": "#008080", "subdomains": [
        { "id": "ai", "label": "AI & Automation" },
        { "id": "devops", "label": "DevOps" },
        { "id": "end-user", "label": "End User & Productivity" },
        { "id": "service-management", "label": "Service Management" },
        { "id": "infrastructure", "label": "Infrastructure & Hosting" }
      ]},
      { "id": "integration", "label": "Integration", "colour": "#6B6B00" },
      { "id": "security", "label": "Security", "colour": "#CC0000" },
      { "id": "data", "label": "Data & Information", "colour": "#800000" }
    ],
    "domains": [
      { "id": "FG_AdultSocial", "label": "Adult Social Care", "layer": "business" },
      { "id": "FG_ChildSocial", "label": "Children's Social Care", "layer": "business" },
      { "id": "FG_Democratic", "label": "Democratic Services", "layer": "business" },
      { "id": "FG_Education", "label": "Education", "layer": "business" },
      { "id": "FG_Highways", "label": "Highways / Transport", "layer": "business" },
      { "id": "FG_Housing", "label": "Housing", "layer": "business" },
      { "id": "FG_Leisure", "label": "Leisure / Culture", "layer": "business" },
      { "id": "FG_Licensing", "label": "Licensing / Regulation", "layer": "business" },
      { "id": "FG_Planning", "label": "Planning / Development", "layer": "business" },
      { "id": "FG_PublicHealth", "label": "Public Health", "layer": "business" },
      { "id": "FG_RevsBens", "label": "Revenues / Benefits", "layer": "business" },
      { "id": "FG_Waste", "label": "Waste Management", "layer": "business" },
      { "id": "FG_BizPlanning", "label": "Business Planning / Performance", "layer": "corporate" },
      { "id": "FG_Comms", "label": "Communications / PR", "layer": "corporate" },
      { "id": "FG_Governance", "label": "Corporate Governance / Risk", "layer": "corporate" },
      { "id": "FG_CustRel", "label": "Customer Relationship / B2C", "layer": "corporate" },
      { "id": "FG_Facilities", "label": "Facilities", "layer": "corporate" },
      { "id": "FG_Financial", "label": "Financial", "layer": "corporate" },
      { "id": "FG_GIS", "label": "Geographical", "layer": "corporate" },
      { "id": "FG_Legal", "label": "Legal / Compliance", "layer": "corporate" },
      { "id": "FG_HR", "label": "Human Resource / Workforce", "layer": "corporate" },
      { "id": "FG_Procurement", "label": "Procurement / B2B", "layer": "corporate" },
      { "id": "CAP_Payments", "label": "Payments", "layer": "capabilities" },
      { "id": "CAP_Forms", "label": "Forms", "layer": "capabilities" },
      { "id": "CAP_Notifications", "label": "Notifications (SMS/Email)", "layer": "capabilities" },
      { "id": "CAP_Identity", "label": "Identity", "layer": "capabilities" },
      { "id": "CAP_Booking", "label": "Booking", "layer": "capabilities" },
      { "id": "FT_AI", "label": "AI & Automation", "layer": "foundational-technology", "subdomain": "ai" },
      { "id": "FT_DevOps", "label": "DevOps", "layer": "foundational-technology", "subdomain": "devops" },
      { "id": "FT_EndUser", "label": "End User & Productivity", "layer": "foundational-technology", "subdomain": "end-user" },
      { "id": "FT_ServiceMgmt", "label": "Service Management", "layer": "foundational-technology", "subdomain": "service-management" },
      { "id": "FT_Infrastructure", "label": "Infrastructure & Hosting", "layer": "foundational-technology", "subdomain": "infrastructure" },
      { "id": "INT_ApiMgmt", "label": "API Management & Gateways", "layer": "integration" },
      { "id": "INT_DataPipelines", "label": "Data Integration & Pipelines", "layer": "integration" },
      { "id": "INT_Middleware", "label": "Message-oriented Middleware", "layer": "integration" },
      { "id": "INT_FileTransfer", "label": "File Transfer Management", "layer": "integration" },
      { "id": "INT_B2B", "label": "Partner (B2B) Integration", "layer": "integration" },
      { "id": "SEC_IAM", "label": "Identity & Access Management", "layer": "security" },
      { "id": "SEC_SOC", "label": "Security Operations (SIEM/SOC)", "layer": "security" },
      { "id": "SEC_Endpoint", "label": "Network & Endpoint Security", "layer": "security" },
      { "id": "SEC_Vulnerability", "label": "Vulnerability Management", "layer": "security" },
      { "id": "SEC_AppData", "label": "Application & Data Security", "layer": "security" },
      { "id": "DATA_BI", "label": "BI & Analytics", "layer": "data" },
      { "id": "DATA_Governance", "label": "Data Governance", "layer": "data" },
      { "id": "DATA_Storage", "label": "Data Storage & Warehousing", "layer": "data" },
      { "id": "DATA_GIS", "label": "Geospatial Data", "layer": "data" },
      { "id": "DATA_Documents", "label": "Document & Records Management", "layer": "data" }
    ],
    "capabilities": [
      { "id": "Cap_Payments", "label": "Payments" },
      { "id": "Cap_Forms", "label": "Forms" },
      { "id": "Cap_Workflow", "label": "Workflow" },
      { "id": "Cap_Identity", "label": "Identity" },
      { "id": "Cap_Booking", "label": "Booking" },
      { "id": "Cap_SMS", "label": "SMS" },
      { "id": "Cap_Email", "label": "Email" },
      { "id": "Cap_Telephony", "label": "Telephony" },
      { "id": "Cap_AgenticAI", "label": "Agentic AI" }
    ]
  },
  "systems": [
    {
      "id": "SYS_PaymentsPlatform",
      "name": "Payments Platform",
      "domains": ["CAP_Payments"],
      "description": "Shared platform providing online payment processing for council services.",
      "lifecycle": "live",
      "identity": { "vendor": "", "users": null, "category": "shared-service", "businessOwner": "", "technicalOwner": "" },
      "contract": { "annualCost": null, "contractEnd": null, "noticePeriod": null },
      "technical": { "hosting": "cloud", "dataModel": "segmented", "portability": "high", "supportModel": "vendor-supported" },
      "compliance": [],
      "capabilities": ["Cap_Payments"],
      "consumers": ["SYS_RevsBens", "SYS_Leisure", "SYS_Highways", "SYS_Waste"],
      "dependencies": []
    },
    {
      "id": "SYS_FormsPlatform",
      "name": "Forms Platform",
      "domains": ["CAP_Forms"],
      "description": "Shared platform for building and managing citizen-facing digital forms.",
      "lifecycle": "live",
      "identity": { "vendor": "", "users": null, "category": "shared-service", "businessOwner": "", "technicalOwner": "" },
      "contract": { "annualCost": null, "contractEnd": null, "noticePeriod": null },
      "technical": { "hosting": "cloud", "dataModel": "segmented", "portability": "high", "supportModel": "vendor-supported" },
      "compliance": [],
      "capabilities": ["Cap_Forms"],
      "consumers": ["SYS_CRM", "SYS_RevsBens", "SYS_Housing", "SYS_Planning"],
      "dependencies": []
    },
    {
      "id": "SYS_NotifyService",
      "name": "Notification Service",
      "domains": ["CAP_Notifications"],
      "description": "Shared service for sending SMS, email, and letter notifications to citizens.",
      "lifecycle": "live",
      "identity": { "vendor": "", "users": null, "category": "shared-service", "businessOwner": "", "technicalOwner": "" },
      "contract": { "annualCost": null, "contractEnd": null, "noticePeriod": null },
      "technical": { "hosting": "cloud", "dataModel": "segmented", "portability": "high", "supportModel": "vendor-supported" },
      "compliance": [],
      "capabilities": ["Cap_SMS", "Cap_Email"],
      "consumers": ["SYS_Care", "SYS_RevsBens", "SYS_Waste", "SYS_CRM"],
      "dependencies": []
    },
    {
      "id": "SYS_IdentityPlatform",
      "name": "Identity Platform",
      "domains": ["CAP_Identity"],
      "description": "Shared platform for citizen identity verification and authentication.",
      "lifecycle": "live",
      "identity": { "vendor": "", "users": null, "category": "shared-service", "businessOwner": "", "technicalOwner": "" },
      "contract": { "annualCost": null, "contractEnd": null, "noticePeriod": null },
      "technical": { "hosting": "cloud", "dataModel": "segmented", "portability": "med", "supportModel": "vendor-supported" },
      "compliance": [],
      "capabilities": ["Cap_Identity"],
      "consumers": ["SYS_Care", "SYS_RevsBens", "SYS_Housing"],
      "dependencies": []
    },
    {
      "id": "SYS_BookingPlatform",
      "name": "Booking Platform",
      "domains": ["CAP_Booking"],
      "description": "Shared platform for managing citizen appointments and service slot bookings.",
      "lifecycle": "live",
      "identity": { "vendor": "", "users": null, "category": "shared-service", "businessOwner": "", "technicalOwner": "" },
      "contract": { "annualCost": null, "contractEnd": null, "noticePeriod": null },
      "technical": { "hosting": "cloud", "dataModel": "segmented", "portability": "high", "supportModel": "vendor-supported" },
      "compliance": [],
      "capabilities": ["Cap_Booking"],
      "consumers": ["SYS_Leisure", "SYS_EnvHealth", "SYS_Highways"],
      "dependencies": []
    },
    {
      "id": "SYS_Care",
      "name": "Social Care System",
      "domains": ["FG_AdultSocial", "FG_ChildSocial"],
      "description": "Core case management system for Adult and Children's statutory social care.",
      "lifecycle": "live",
      "identity": { "vendor": "", "users": null, "category": "line-of-business", "businessOwner": "", "technicalOwner": "" },
      "contract": { "annualCost": null, "contractEnd": null, "noticePeriod": null },
      "technical": { "hosting": "on-prem", "dataModel": "monolithic", "portability": "low", "supportModel": "vendor-supported" },
      "compliance": [],
      "capabilities": ["Cap_Workflow", "Cap_Forms"],
      "consumers": ["SYS_Income"],
      "dependencies": ["SYS_ERP"]
    },
    {
      "id": "SYS_Waste",
      "name": "Waste System",
      "domains": ["FG_Waste"],
      "description": "Operational system for managing domestic/commercial waste collection and fleet routing.",
      "lifecycle": "live",
      "identity": { "vendor": "", "users": null, "category": "line-of-business", "businessOwner": "", "technicalOwner": "" },
      "contract": { "annualCost": null, "contractEnd": null, "noticePeriod": null },
      "technical": { "hosting": "cloud", "dataModel": "monolithic", "portability": "med", "supportModel": "vendor-supported" },
      "compliance": [],
      "capabilities": ["Cap_Forms", "Cap_Booking"],
      "consumers": [],
      "dependencies": ["SYS_GIS"]
    },
    {
      "id": "SYS_Elections",
      "name": "Electoral System",
      "domains": ["FG_Democratic"],
      "description": "Specialist system for electoral registration and ballot management.",
      "lifecycle": "live",
      "identity": { "vendor": "", "users": null, "category": "line-of-business", "businessOwner": "", "technicalOwner": "" },
      "contract": { "annualCost": null, "contractEnd": null, "noticePeriod": null },
      "technical": { "hosting": "on-prem", "dataModel": "monolithic", "portability": "low", "supportModel": "vendor-supported" },
      "compliance": [],
      "capabilities": ["Cap_Forms"],
      "consumers": [],
      "dependencies": []
    },
    {
      "id": "SYS_RevsBens",
      "name": "Revenues & Benefits System",
      "domains": ["FG_RevsBens"],
      "description": "System for processing council tax, business rates, and housing benefits.",
      "lifecycle": "live",
      "identity": { "vendor": "", "users": null, "category": "line-of-business", "businessOwner": "", "technicalOwner": "" },
      "contract": { "annualCost": null, "contractEnd": null, "noticePeriod": null },
      "technical": { "hosting": "on-prem", "dataModel": "monolithic", "portability": "low", "supportModel": "vendor-supported" },
      "compliance": [],
      "capabilities": ["Cap_Forms", "Cap_Payments"],
      "consumers": [],
      "dependencies": ["SYS_ERP", "SYS_Income"]
    },
    {
      "id": "SYS_EnvHealth",
      "name": "Environmental Health System",
      "domains": ["FG_Licensing"],
      "description": "Regulatory system for environmental protection, trading standards, and food safety.",
      "lifecycle": "live",
      "identity": { "vendor": "", "users": null, "category": "line-of-business", "businessOwner": "", "technicalOwner": "" },
      "contract": { "annualCost": null, "contractEnd": null, "noticePeriod": null },
      "technical": { "hosting": "cloud", "dataModel": "monolithic", "portability": "med", "supportModel": "vendor-supported" },
      "compliance": [],
      "capabilities": ["Cap_Forms", "Cap_Booking"],
      "consumers": [],
      "dependencies": ["SYS_GIS"]
    },
    {
      "id": "SYS_Housing",
      "name": "Housing Management System",
      "domains": ["FG_Housing"],
      "description": "System covering tenancies, allocations, rents, and repairs.",
      "lifecycle": "live",
      "identity": { "vendor": "", "users": null, "category": "line-of-business", "businessOwner": "", "technicalOwner": "" },
      "contract": { "annualCost": null, "contractEnd": null, "noticePeriod": null },
      "technical": { "hosting": "on-prem", "dataModel": "monolithic", "portability": "low", "supportModel": "vendor-supported" },
      "compliance": [],
      "capabilities": ["Cap_Forms", "Cap_Workflow"],
      "consumers": [],
      "dependencies": ["SYS_ERP"]
    },
    {
      "id": "SYS_Leisure",
      "name": "Leisure Management System",
      "domains": ["FG_Leisure"],
      "description": "Booking and facility management platform for leisure centres and cultural venues.",
      "lifecycle": "live",
      "identity": { "vendor": "", "users": null, "category": "line-of-business", "businessOwner": "", "technicalOwner": "" },
      "contract": { "annualCost": null, "contractEnd": null, "noticePeriod": null },
      "technical": { "hosting": "cloud", "dataModel": "segmented", "portability": "med", "supportModel": "vendor-supported" },
      "compliance": [],
      "capabilities": ["Cap_Booking", "Cap_Payments"],
      "consumers": [],
      "dependencies": []
    },
    {
      "id": "SYS_Planning",
      "name": "Planning & Building Control System",
      "domains": ["FG_Planning"],
      "description": "System managing spatial planning applications and building control.",
      "lifecycle": "live",
      "identity": { "vendor": "", "users": null, "category": "line-of-business", "businessOwner": "", "technicalOwner": "" },
      "contract": { "annualCost": null, "contractEnd": null, "noticePeriod": null },
      "technical": { "hosting": "on-prem", "dataModel": "monolithic", "portability": "low", "supportModel": "vendor-supported" },
      "compliance": [],
      "capabilities": ["Cap_Forms"],
      "consumers": [],
      "dependencies": ["SYS_GIS"]
    },
    {
      "id": "SYS_Highways",
      "name": "Highways Management System",
      "domains": ["FG_Highways"],
      "description": "Asset management system for roads, street lighting, and parking.",
      "lifecycle": "live",
      "identity": { "vendor": "", "users": null, "category": "line-of-business", "businessOwner": "", "technicalOwner": "" },
      "contract": { "annualCost": null, "contractEnd": null, "noticePeriod": null },
      "technical": { "hosting": "hybrid", "dataModel": "monolithic", "portability": "low", "supportModel": "vendor-supported" },
      "compliance": [],
      "capabilities": ["Cap_Forms", "Cap_Booking", "Cap_Payments"],
      "consumers": [],
      "dependencies": ["SYS_GIS"]
    },
    {
      "id": "SYS_Lib",
      "name": "Library Management System",
      "domains": ["FG_Leisure"],
      "description": "System for cataloguing, loans, and membership management.",
      "lifecycle": "live",
      "identity": { "vendor": "", "users": null, "category": "line-of-business", "businessOwner": "", "technicalOwner": "" },
      "contract": { "annualCost": null, "contractEnd": null, "noticePeriod": null },
      "technical": { "hosting": "cloud", "dataModel": "segmented", "portability": "med", "supportModel": "shared" },
      "compliance": [],
      "capabilities": ["Cap_Booking"],
      "consumers": [],
      "dependencies": []
    },
    {
      "id": "SYS_Education",
      "name": "Education Management System",
      "domains": ["FG_Education"],
      "description": "Management information system for schools, pupil admissions, and early years.",
      "lifecycle": "live",
      "identity": { "vendor": "", "users": null, "category": "line-of-business", "businessOwner": "", "technicalOwner": "" },
      "contract": { "annualCost": null, "contractEnd": null, "noticePeriod": null },
      "technical": { "hosting": "cloud", "dataModel": "monolithic", "portability": "med", "supportModel": "vendor-supported" },
      "compliance": [],
      "capabilities": ["Cap_Forms"],
      "consumers": [],
      "dependencies": []
    },
    {
      "id": "SYS_ERP",
      "name": "Corporate ERP",
      "domains": ["FG_Financial", "FG_Procurement"],
      "description": "Enterprise Resource Planning for core back-office finance and procurement.",
      "lifecycle": "live",
      "identity": { "vendor": "", "users": null, "category": "corporate", "businessOwner": "", "technicalOwner": "" },
      "contract": { "annualCost": null, "contractEnd": null, "noticePeriod": null },
      "technical": { "hosting": "on-prem", "dataModel": "monolithic", "portability": "low", "supportModel": "vendor-supported" },
      "compliance": [],
      "capabilities": ["Cap_Payments", "Cap_Workflow"],
      "consumers": ["SYS_Care", "SYS_RevsBens", "SYS_Housing"],
      "dependencies": []
    },
    {
      "id": "SYS_CRM",
      "name": "Corporate CRM",
      "domains": ["FG_CustRel"],
      "description": "Centralised system for managing citizen interactions and service requests.",
      "lifecycle": "live",
      "identity": { "vendor": "", "users": null, "category": "corporate", "businessOwner": "", "technicalOwner": "" },
      "contract": { "annualCost": null, "contractEnd": null, "noticePeriod": null },
      "technical": { "hosting": "cloud", "dataModel": "segmented", "portability": "med", "supportModel": "vendor-supported" },
      "compliance": [],
      "capabilities": ["Cap_Forms", "Cap_Workflow"],
      "consumers": [],
      "dependencies": []
    },
    {
      "id": "SYS_HRPayroll",
      "name": "HR & Payroll System",
      "domains": ["FG_HR"],
      "description": "Human resources, staff management, recruitment, and payroll processing.",
      "lifecycle": "live",
      "identity": { "vendor": "", "users": null, "category": "corporate", "businessOwner": "", "technicalOwner": "" },
      "contract": { "annualCost": null, "contractEnd": null, "noticePeriod": null },
      "technical": { "hosting": "cloud", "dataModel": "monolithic", "portability": "low", "supportModel": "vendor-supported" },
      "compliance": [],
      "capabilities": ["Cap_Workflow"],
      "consumers": [],
      "dependencies": ["SYS_ERP"]
    },
    {
      "id": "SYS_Income",
      "name": "Income Management System",
      "domains": ["FG_Financial"],
      "description": "Corporate income management, receipting, and cash management platform.",
      "lifecycle": "live",
      "identity": { "vendor": "", "users": null, "category": "corporate", "businessOwner": "", "technicalOwner": "" },
      "contract": { "annualCost": null, "contractEnd": null, "noticePeriod": null },
      "technical": { "hosting": "on-prem", "dataModel": "monolithic", "portability": "low", "supportModel": "vendor-supported" },
      "compliance": [],
      "capabilities": ["Cap_Payments"],
      "consumers": [],
      "dependencies": ["SYS_ERP"]
    },
    {
      "id": "SYS_GIS",
      "name": "GIS Platform",
      "domains": ["FG_GIS", "DATA_GIS"],
      "description": "Geographic information system for mapping, spatial analysis, and gazetteer management.",
      "lifecycle": "live",
      "identity": { "vendor": "", "users": null, "category": "corporate", "businessOwner": "", "technicalOwner": "" },
      "contract": { "annualCost": null, "contractEnd": null, "noticePeriod": null },
      "technical": { "hosting": "on-prem", "dataModel": "monolithic", "portability": "low", "supportModel": "vendor-supported" },
      "compliance": [],
      "capabilities": [],
      "consumers": ["SYS_Planning", "SYS_Highways", "SYS_Waste", "SYS_EnvHealth"],
      "dependencies": []
    },
    {
      "id": "SYS_CloudPlatform",
      "name": "Cloud Platform",
      "domains": ["FT_Infrastructure"],
      "description": "Primary cloud infrastructure platform (IaaS/PaaS) for hosting council workloads.",
      "lifecycle": "live",
      "identity": { "vendor": "", "users": null, "category": "platform", "businessOwner": "", "technicalOwner": "" },
      "contract": { "annualCost": null, "contractEnd": null, "noticePeriod": null },
      "technical": { "hosting": "cloud", "dataModel": "segmented", "portability": "med", "supportModel": "vendor-supported" },
      "compliance": [],
      "capabilities": [],
      "consumers": [],
      "dependencies": []
    },
    {
      "id": "SYS_HCI",
      "name": "On-Premises Infrastructure",
      "domains": ["FT_Infrastructure"],
      "description": "Hyperconverged or traditional server infrastructure for on-premises workloads.",
      "lifecycle": "retiring",
      "identity": { "vendor": "", "users": null, "category": "platform", "businessOwner": "", "technicalOwner": "" },
      "contract": { "annualCost": null, "contractEnd": null, "noticePeriod": null },
      "technical": { "hosting": "on-prem", "dataModel": "monolithic", "portability": "low", "supportModel": "in-house" },
      "compliance": [],
      "capabilities": [],
      "consumers": [],
      "dependencies": []
    },
    {
      "id": "SYS_ITSM",
      "name": "ITSM Platform",
      "domains": ["FT_ServiceMgmt"],
      "description": "IT Service Management platform for service desk, change, and incident management.",
      "lifecycle": "live",
      "identity": { "vendor": "", "users": null, "category": "platform", "businessOwner": "", "technicalOwner": "" },
      "contract": { "annualCost": null, "contractEnd": null, "noticePeriod": null },
      "technical": { "hosting": "cloud", "dataModel": "segmented", "portability": "med", "supportModel": "vendor-supported" },
      "compliance": [],
      "capabilities": ["Cap_Workflow"],
      "consumers": [],
      "dependencies": []
    },
    {
      "id": "SYS_UC",
      "name": "Unified Communications",
      "domains": ["FT_EndUser"],
      "description": "Collaboration and communication platform (Teams, Zoom, etc.) for staff.",
      "lifecycle": "live",
      "identity": { "vendor": "", "users": null, "category": "platform", "businessOwner": "", "technicalOwner": "" },
      "contract": { "annualCost": null, "contractEnd": null, "noticePeriod": null },
      "technical": { "hosting": "cloud", "dataModel": "segmented", "portability": "med", "supportModel": "vendor-supported" },
      "compliance": [],
      "capabilities": ["Cap_Telephony"],
      "consumers": [],
      "dependencies": []
    },
    {
      "id": "SYS_MDM",
      "name": "Device Management",
      "domains": ["FT_EndUser"],
      "description": "Mobile device management and endpoint provisioning for council devices.",
      "lifecycle": "live",
      "identity": { "vendor": "", "users": null, "category": "platform", "businessOwner": "", "technicalOwner": "" },
      "contract": { "annualCost": null, "contractEnd": null, "noticePeriod": null },
      "technical": { "hosting": "cloud", "dataModel": "segmented", "portability": "high", "supportModel": "vendor-supported" },
      "compliance": [],
      "capabilities": [],
      "consumers": [],
      "dependencies": ["SYS_IAM"]
    },
    {
      "id": "SYS_AIML",
      "name": "AI/ML Platform",
      "domains": ["FT_AI"],
      "description": "Platform for building, training, and deploying AI/ML models and automation.",
      "lifecycle": "planned",
      "identity": { "vendor": "", "users": null, "category": "platform", "businessOwner": "", "technicalOwner": "" },
      "contract": { "annualCost": null, "contractEnd": null, "noticePeriod": null },
      "technical": { "hosting": "cloud", "dataModel": "segmented", "portability": "high", "supportModel": "vendor-supported" },
      "compliance": [],
      "capabilities": ["Cap_AgenticAI"],
      "consumers": [],
      "dependencies": ["SYS_CloudPlatform"]
    },
    {
      "id": "SYS_CICD",
      "name": "CI/CD Platform",
      "domains": ["FT_DevOps"],
      "description": "Continuous integration and deployment pipeline for council applications.",
      "lifecycle": "live",
      "identity": { "vendor": "", "users": null, "category": "platform", "businessOwner": "", "technicalOwner": "" },
      "contract": { "annualCost": null, "contractEnd": null, "noticePeriod": null },
      "technical": { "hosting": "cloud", "dataModel": "segmented", "portability": "high", "supportModel": "in-house" },
      "compliance": [],
      "capabilities": [],
      "consumers": [],
      "dependencies": ["SYS_CloudPlatform"]
    },
    {
      "id": "SYS_Monitoring",
      "name": "Monitoring & Observability",
      "domains": ["FT_DevOps"],
      "description": "Platform for application and infrastructure monitoring, alerting, and logging.",
      "lifecycle": "live",
      "identity": { "vendor": "", "users": null, "category": "platform", "businessOwner": "", "technicalOwner": "" },
      "contract": { "annualCost": null, "contractEnd": null, "noticePeriod": null },
      "technical": { "hosting": "cloud", "dataModel": "segmented", "portability": "med", "supportModel": "vendor-supported" },
      "compliance": [],
      "capabilities": [],
      "consumers": [],
      "dependencies": []
    },
    {
      "id": "SYS_iPaaS",
      "name": "Integration Platform",
      "domains": ["INT_ApiMgmt", "INT_DataPipelines"],
      "description": "Integration platform-as-a-service for connecting systems via APIs and data pipelines.",
      "lifecycle": "live",
      "identity": { "vendor": "", "users": null, "category": "platform", "businessOwner": "", "technicalOwner": "" },
      "contract": { "annualCost": null, "contractEnd": null, "noticePeriod": null },
      "technical": { "hosting": "cloud", "dataModel": "segmented", "portability": "med", "supportModel": "vendor-supported" },
      "compliance": [],
      "capabilities": [],
      "consumers": [],
      "dependencies": ["SYS_CloudPlatform"]
    },
    {
      "id": "SYS_MFT",
      "name": "Managed File Transfer",
      "domains": ["INT_FileTransfer"],
      "description": "Secure file transfer system for exchanging data with partners and government bodies.",
      "lifecycle": "live",
      "identity": { "vendor": "", "users": null, "category": "platform", "businessOwner": "", "technicalOwner": "" },
      "contract": { "annualCost": null, "contractEnd": null, "noticePeriod": null },
      "technical": { "hosting": "on-prem", "dataModel": "monolithic", "portability": "low", "supportModel": "vendor-supported" },
      "compliance": [],
      "capabilities": [],
      "consumers": [],
      "dependencies": []
    },
    {
      "id": "SYS_IAM",
      "name": "IAM Platform",
      "domains": ["SEC_IAM"],
      "description": "Identity and access management for staff: directory services, SSO, MFA, conditional access.",
      "lifecycle": "live",
      "identity": { "vendor": "", "users": null, "category": "platform", "businessOwner": "", "technicalOwner": "" },
      "contract": { "annualCost": null, "contractEnd": null, "noticePeriod": null },
      "technical": { "hosting": "cloud", "dataModel": "segmented", "portability": "med", "supportModel": "vendor-supported" },
      "compliance": ["cyber-essentials"],
      "capabilities": ["Cap_Identity"],
      "consumers": [],
      "dependencies": []
    },
    {
      "id": "SYS_SIEM",
      "name": "SIEM / SOC Platform",
      "domains": ["SEC_SOC"],
      "description": "Security information and event management for threat detection and incident response.",
      "lifecycle": "live",
      "identity": { "vendor": "", "users": null, "category": "platform", "businessOwner": "", "technicalOwner": "" },
      "contract": { "annualCost": null, "contractEnd": null, "noticePeriod": null },
      "technical": { "hosting": "cloud", "dataModel": "segmented", "portability": "med", "supportModel": "managed-service" },
      "compliance": ["cyber-essentials"],
      "capabilities": [],
      "consumers": [],
      "dependencies": []
    },
    {
      "id": "SYS_EDR",
      "name": "Endpoint Protection",
      "domains": ["SEC_Endpoint"],
      "description": "Endpoint detection and response (EDR) and network security platform.",
      "lifecycle": "live",
      "identity": { "vendor": "", "users": null, "category": "platform", "businessOwner": "", "technicalOwner": "" },
      "contract": { "annualCost": null, "contractEnd": null, "noticePeriod": null },
      "technical": { "hosting": "cloud", "dataModel": "segmented", "portability": "high", "supportModel": "vendor-supported" },
      "compliance": ["cyber-essentials"],
      "capabilities": [],
      "consumers": [],
      "dependencies": []
    },
    {
      "id": "SYS_VulnScan",
      "name": "Vulnerability Scanner",
      "domains": ["SEC_Vulnerability"],
      "description": "Automated vulnerability scanning and patch compliance assessment tool.",
      "lifecycle": "live",
      "identity": { "vendor": "", "users": null, "category": "platform", "businessOwner": "", "technicalOwner": "" },
      "contract": { "annualCost": null, "contractEnd": null, "noticePeriod": null },
      "technical": { "hosting": "cloud", "dataModel": "segmented", "portability": "high", "supportModel": "vendor-supported" },
      "compliance": ["cyber-essentials"],
      "capabilities": [],
      "consumers": [],
      "dependencies": []
    },
    {
      "id": "SYS_DataWarehouse",
      "name": "Data Warehouse",
      "domains": ["DATA_Storage", "DATA_BI"],
      "description": "Central data warehouse or lakehouse for analytics, reporting, and statutory returns.",
      "lifecycle": "live",
      "identity": { "vendor": "", "users": null, "category": "platform", "businessOwner": "", "technicalOwner": "" },
      "contract": { "annualCost": null, "contractEnd": null, "noticePeriod": null },
      "technical": { "hosting": "cloud", "dataModel": "segmented", "portability": "med", "supportModel": "in-house" },
      "compliance": [],
      "capabilities": [],
      "consumers": [],
      "dependencies": ["SYS_CloudPlatform"]
    },
    {
      "id": "SYS_BI",
      "name": "BI & Reporting Platform",
      "domains": ["DATA_BI"],
      "description": "Business intelligence and data visualisation platform for council reporting.",
      "lifecycle": "live",
      "identity": { "vendor": "", "users": null, "category": "platform", "businessOwner": "", "technicalOwner": "" },
      "contract": { "annualCost": null, "contractEnd": null, "noticePeriod": null },
      "technical": { "hosting": "cloud", "dataModel": "segmented", "portability": "med", "supportModel": "vendor-supported" },
      "compliance": [],
      "capabilities": [],
      "consumers": [],
      "dependencies": ["SYS_DataWarehouse"]
    },
    {
      "id": "SYS_DMS",
      "name": "Document Management System",
      "domains": ["DATA_Documents"],
      "description": "Electronic document and records management for council correspondence and files.",
      "lifecycle": "live",
      "identity": { "vendor": "", "users": null, "category": "platform", "businessOwner": "", "technicalOwner": "" },
      "contract": { "annualCost": null, "contractEnd": null, "noticePeriod": null },
      "technical": { "hosting": "on-prem", "dataModel": "monolithic", "portability": "low", "supportModel": "vendor-supported" },
      "compliance": [],
      "capabilities": [],
      "consumers": [],
      "dependencies": []
    }
  ]
}
